pmp_manip/__init__.py
pmp_manip/important_consts.py
pmp_manip/builtin_extension_source/LICENSE
pmp_manip/builtin_extension_source/README.md
pmp_manip/builtin_extension_source/builtin_extensions/DTcameracontrols.js
pmp_manip/builtin_extension_source/builtin_extensions/Gamepad.js
pmp_manip/builtin_extension_source/builtin_extensions/SPjavascriptV2.js
pmp_manip/builtin_extension_source/builtin_extensions/blockly2math.js
pmp_manip/builtin_extension_source/builtin_extensions/boost.js
pmp_manip/builtin_extension_source/builtin_extensions/canvas.js
pmp_manip/builtin_extension_source/builtin_extensions/colors.js
pmp_manip/builtin_extension_source/builtin_extensions/ev3.js
pmp_manip/builtin_extension_source/builtin_extensions/fr3d.js
pmp_manip/builtin_extension_source/builtin_extensions/gameutils.js
pmp_manip/builtin_extension_source/builtin_extensions/gdxfor.js
pmp_manip/builtin_extension_source/builtin_extensions/iygPerlin.js
pmp_manip/builtin_extension_source/builtin_extensions/jg3d.js
pmp_manip/builtin_extension_source/builtin_extensions/jg3dVr.js
pmp_manip/builtin_extension_source/builtin_extensions/jgAnimation.js
pmp_manip/builtin_extension_source/builtin_extensions/jgBestExtension.js
pmp_manip/builtin_extension_source/builtin_extensions/jgChristmas.js
pmp_manip/builtin_extension_source/builtin_extensions/jgClones.js
pmp_manip/builtin_extension_source/builtin_extensions/jgDebugging.js
pmp_manip/builtin_extension_source/builtin_extensions/jgDev.js
pmp_manip/builtin_extension_source/builtin_extensions/jgDooDoo.js
pmp_manip/builtin_extension_source/builtin_extensions/jgEasySave.js
pmp_manip/builtin_extension_source/builtin_extensions/jgExtendedAudio.js
pmp_manip/builtin_extension_source/builtin_extensions/jgFiles.js
pmp_manip/builtin_extension_source/builtin_extensions/jgIframe.js
pmp_manip/builtin_extension_source/builtin_extensions/jgInterfaces.js
pmp_manip/builtin_extension_source/builtin_extensions/jgJSON.js
py_pmp_manip-1.2.0.dist-info/licenses/LICENSE
py_pmp_manip-1.2.0.dist-info/METADATA
py_pmp_manip-1.2.0.dist-info/WHEEL
py_pmp_manip-1.2.0.dist-info/top_level.txt
py_pmp_manip-1.2.0.dist-info/RECORD
