Metadata-Version: 2.4
Name: py-pmp-manip
Version: 1.2.0
Summary: Python tool for creating, editing and inspecting Penguinmod(.pmp) and Scratch(.sb3) files.
Author-email: GermanCodeEngineer <germancodeengineer@proton.me>
License: GPL-3.0-or-later
Project-URL: Homepage, https://github.com/GermanCodeEngineer/py-pmp-manip/
Project-URL: Repository, https://github.com/GermanCodeEngineer/py-pmp-manip/
Project-URL: Issues, https://github.com/GermanCodeEngineer/py-pmp-manip/issues/
Classifier: Development Status :: 5 - Production/Stable
Classifier: Programming Language :: Python :: 3.12
Classifier: Programming Language :: Python :: 3.13
Classifier: Programming Language :: Python :: 3.14
Classifier: License :: OSI Approved :: GNU General Public License v3 or later (GPLv3+)
Classifier: Operating System :: OS Independent
Requires-Python: >=3.12
License-File: LICENSE
Requires-Dist: Pillow~=12.0
Requires-Dist: Requests~=2.32
Requires-Dist: colorama~=0.4
Requires-Dist: lxml~=6.0
Requires-Dist: pydub_ng~=0.2
Requires-Dist: tree_sitter~=0.25
Requires-Dist: tree_sitter_javascript~=0.25
Requires-Dist: validators~=0.35
Provides-Extra: dev
Requires-Dist: graphviz~=0.21; extra == "dev"
Requires-Dist: pytest~=9.0; extra == "dev"
Requires-Dist: tomlkit~=0.13; extra == "dev"
Requires-Dist: coverage~=7.13; extra == "dev"
Requires-Dist: pipreqs~=0.4; extra == "dev"
Dynamic: license-file
